<?xml version="1.0" encoding="utf-8"?>
<SoundBanksInfo Platform="Mac" BasePlatform="Mac" SchemaVersion="12" SoundbankVersion="140">
	<RootPaths>
		<ProjectRoot>G:\Unity School Projects\Hip Hop Assasins Prototype\HipHopAssassinsPrototype\HipHopAssassins\HipHopAssassins_WwiseProject\</ProjectRoot>
		<SourceFilesRoot>G:\Unity School Projects\Hip Hop Assasins Prototype\HipHopAssassinsPrototype\HipHopAssassins\HipHopAssassins_WwiseProject\.cache\Mac\</SourceFilesRoot>
		<SoundBanksRoot>G:\Unity School Projects\Hip Hop Assasins Prototype\HipHopAssassinsPrototype\HipHopAssassins\HipHopAssassins_WwiseProject\GeneratedSoundBanks\Mac\</SoundBanksRoot>
		<ExternalSourcesInputFile></ExternalSourcesInputFile>
		<ExternalSourcesOutputRoot>G:\Unity School Projects\Hip Hop Assasins Prototype\HipHopAssassinsPrototype\HipHopAssassins\HipHopAssassins_WwiseProject\GeneratedSoundBanks\Mac</ExternalSourcesOutputRoot>
	</RootPaths>
	<DialogueEvents/>
	<StreamedFiles/>
	<MediaFilesNotInAnyBank/>
	<SoundBanks>
		<SoundBank Id="1229948536" Language="SFX" Hash="3046224877">
			<ObjectPath>\SoundBanks\Default Work Unit\Environment</ObjectPath>
			<ShortName>Environment</ShortName>
			<Path>Environment.bnk</Path>
			<IncludedEvents>
				<Event Id="713430530" Name="Play_Learning_the_Basics" ObjectPath="\Events\Default Work Unit\Play_Learning_the_Basics" DurationType="OneShot" DurationMin="52.173923" DurationMax="52.173923">
					<IncludedMemoryFiles>
						<File Id="973058546" Language="SFX">
							<ShortName>Learning the Basics.wav</ShortName>
							<Path>SFX\Learning the Basics_D79FB2B7.wem</Path>
						</File>
					</IncludedMemoryFiles>
				</Event>
			</IncludedEvents>
			<IncludedMemoryFiles>
				<File Id="973058546" Language="SFX">
					<ShortName>Learning the Basics.wav</ShortName>
					<Path>SFX\Learning the Basics_D79FB2B7.wem</Path>
				</File>
			</IncludedMemoryFiles>
		</SoundBank>
		<SoundBank Id="1355168291" Language="SFX" Hash="2754342975">
			<ObjectPath>Init</ObjectPath>
			<ShortName>Init</ShortName>
			<Path>Init.bnk</Path>
		</SoundBank>
	</SoundBanks>
</SoundBanksInfo>
